profiwiki/__init__.py
profiwiki/patch.py
profiwiki/profiwiki_cmd.py
profiwiki/profiwiki_core.py
profiwiki/pw_container.py
profiwiki/version.py
profiwiki/resources/install_fontawesome.sh
profiwiki/resources/install_plantuml.sh
profiwiki-0.7.0.dist-info/METADATA
profiwiki-0.7.0.dist-info/WHEEL
profiwiki-0.7.0.dist-info/entry_points.txt
profiwiki-0.7.0.dist-info/licenses/LICENSE
profiwiki-0.7.0.dist-info/RECORD
