Metadata-Version: 2.4
Name: ProfiWiki
Version: 0.7.0
Dynamic: Summary
Project-URL: Home, https://github.com/BITPlan/ProfiWiki
Project-URL: Documentation, https://wiki.bitplan.com/index.php/ProfiWiki
Project-URL: Source, https://github.com/BITPlan/ProfiWiki
Author-email: Wolfgang Fahl <wf@bitplan.com>
Maintainer-email: Wolfgang Fahl <wf@bitplan.com>
License-Expression: Apache-2.0
License-File: LICENSE
Classifier: Development Status :: 4 - Beta
Classifier: Environment :: Web Environment
Classifier: Intended Audience :: Developers
Classifier: Intended Audience :: Education
Classifier: Intended Audience :: Science/Research
Classifier: License :: OSI Approved :: Apache Software License
Classifier: Operating System :: OS Independent
Classifier: Programming Language :: Python :: 3 :: Only
Classifier: Programming Language :: Python :: 3.10
Classifier: Programming Language :: Python :: 3.11
Classifier: Programming Language :: Python :: 3.12
Classifier: Programming Language :: Python :: 3.13
Classifier: Topic :: Software Development :: Libraries :: Python Modules
Requires-Python: >=3.10
Requires-Dist: py-3rdparty-mediawiki>=0.18.0
Requires-Dist: pybasemkit>=0.1.3
Requires-Dist: pymediawikidocker>=0.23.1
Provides-Extra: test
Requires-Dist: green; extra == 'test'
Requires-Dist: ptvsd; extra == 'test'
Requires-Dist: pydevd; extra == 'test'
